gmosfc/__init__.py
gmosfc/fc_gaia.py
gmosfc/fc_skyquery.py
gmosfc/fcutils.py
gmosfc-0.0.11.dist-info/LICENSE
gmosfc-0.0.11.dist-info/METADATA
gmosfc-0.0.11.dist-info/WHEEL
gmosfc-0.0.11.dist-info/top_level.txt
gmosfc-0.0.11.dist-info/RECORD
