Metadata-Version: 2.1
Name: gmosfc
Version: 0.0.11
Summary: Handy GMOS finding chart generator
Home-page: https://github.com/astroquackers/gmosfc/
Author: Venu Kalari
Author-email: vkalari@gemini.edu
License: MIT
Platform: UNKNOWN
Classifier: Development Status :: 4 - Beta
Classifier: License :: OSI Approved :: MIT License
Classifier: Operating System :: OS Independent
Classifier: Programming Language :: Python
Classifier: Intended Audience :: Science/Research
Classifier: Topic :: Scientific/Engineering :: Astronomy
Requires-Dist: numpy (>=1.11)
Requires-Dist: astropy (>=4.0)
Requires-Dist: astroquery (>=0.4)
Requires-Dist: matplotlib (>=3.1.1)
Requires-Dist: photutils (>=0.7.2)
Requires-Dist: APLpy (>=2.0.2)
